<list>
  <paciente>
    <idpaciente>12</idpaciente>
    <nome>Pablo</nome>
    <cpf>11111111111</cpf>
    <email>p@gmail.com</email>
  </paciente>
  <paciente>
    <idpaciente>13</idpaciente>
    <nome>Bruno N.</nome>
    <cpf>00739504088</cpf>
    <email>bruno@gmail.com</email>
    <idfacebook>1485431984827311</idfacebook>
  </paciente>
  <paciente>
    <idpaciente>14</idpaciente>
    <nome>Mariazinha </nome>
    <cpf>11111111111</cpf>
    <email>maria@gmail.com</email>
    <idfacebook>152218552179920</idfacebook>
  </paciente>
  <paciente>
    <idpaciente>15</idpaciente>
    <nome>Fabricio Pretto</nome>
    <cpf>11111111111</cpf>
    <email>fabricio@gmail.com</email>
    <idfacebook>1975383782734506</idfacebook>
  </paciente>
  <paciente>
    <idpaciente>16</idpaciente>
    <nome>Matias</nome>
    <cpf>11111111111</cpf>
    <email>dasd@dasd.com</email>
  </paciente>
  <paciente>
    <idpaciente>17</idpaciente>
    <nome>Teste</nome>
    <cpf>11111111111</cpf>
    <email>dasd@dasd.com</email>
  </paciente>
  <paciente>
    <idpaciente>18</idpaciente>
    <nome>Brunao</nome>
    <cpf>11111111111</cpf>
    <email>dasda@asd.com</email>
  </paciente>
  <paciente>
    <idpaciente>19</idpaciente>
    <nome>Lila</nome>
    <cpf>11111111111</cpf>
    <email>lila@gmail.com</email>
  </paciente>
</list>
